{
  "code": "E06",
  "kind": "category",
  "label": "Thyreoiditis",
  "rubrics": {
    "preferred": "Thyreoiditis",
    "exclusion": "Postpartale ThyreoiditisO90.5"
  },
  "children": [
    {
      "code": "E06.0",
      "kind": "category",
      "label": "Akute Thyreoiditis",
      "rubrics": {
        "preferred": "Akute Thyreoiditis",
        "inclusion": "Thyreoiditis:\n\t\t\t\tpyogen",
        "coding-hint": "Soll der Infektionserreger angegeben werden, ist eine zusätzliche Schlüsselnummer (B95-B98) zu benutzen."
      },
      "children": []
    },
    {
      "code": "E06.1",
      "kind": "category",
      "label": "Subakute Thyreoiditis",
      "rubrics": {
        "preferred": "Subakute Thyreoiditis",
        "inclusion": "Thyreoiditis:\n\t\t\t\tRiesenzell-",
        "exclusion": "AutoimmunthyreoiditisE06.3"
      },
      "children": []
    },
    {
      "code": "E06.2",
      "kind": "category",
      "label": "Chronische Thyreoiditis mit transitorischer Hyperthyreose",
      "rubrics": {
        "preferred": "Chronische Thyreoiditis mit transitorischer Hyperthyreose",
        "exclusion": "AutoimmunthyreoiditisE06.3"
      },
      "children": []
    },
    {
      "code": "E06.3",
      "kind": "category",
      "label": "Autoimmunthyreoiditis",
      "rubrics": {
        "preferred": "Autoimmunthyreoiditis",
        "inclusion": "Struma lymphomatosa [Hashimoto]"
      },
      "children": []
    },
    {
      "code": "E06.4",
      "kind": "category",
      "label": "Arzneimittelinduzierte Thyreoiditis",
      "rubrics": {
        "preferred": "Arzneimittelinduzierte Thyreoiditis",
        "coding-hint": "Soll die Substanz angegeben werden, ist eine zusätzliche Schlüsselnummer (Kapitel XX) zu benutzen."
      },
      "children": []
    },
    {
      "code": "E06.5",
      "kind": "category",
      "label": "Sonstige chronische Thyreoiditis",
      "rubrics": {
        "preferred": "Sonstige chronische Thyreoiditis",
        "inclusion": "Thyreoiditis:\n\t\t\t\tRiedel-Struma"
      },
      "children": []
    },
    {
      "code": "E06.9",
      "kind": "category",
      "label": "Thyreoiditis, nicht näher bezeichnet",
      "rubrics": {
        "preferred": "Thyreoiditis, nicht näher bezeichnet"
      },
      "children": []
    }
  ]
}