{"code": "N30", "kind": "category", "label": "Zystitis", "rubrics": {"preferred": "Zystitis", "coding-hint": "Soll der Infektionserreger (B95-B98) oder das verursachende exogene Agens (Kapitel XX) angegeben werden, ist eine zus채tzliche Schl체sselnummer zu benutzen.", "exclusion": "ProstatazystitisN41.3"}, "children": [{"code": "N30.0", "kind": "category", "label": "Akute Zystitis", "rubrics": {"preferred": "Akute Zystitis", "exclusion": "TrigonumzystitisN30.3"}, "children": []}, {"code": "N30.1", "kind": "category", "label": "Interstitielle Zystitis (chronisch)", "rubrics": {"preferred": "Interstitielle Zystitis (chronisch)"}, "children": []}, {"code": "N30.2", "kind": "category", "label": "Sonstige chronische Zystitis", "rubrics": {"preferred": "Sonstige chronische Zystitis"}, "children": []}, {"code": "N30.3", "kind": "category", "label": "Trigonumzystitis", "rubrics": {"preferred": "Trigonumzystitis", "inclusion": "Urethrotrigonumzystitis"}, "children": []}, {"code": "N30.4", "kind": "category", "label": "Strahlenzystitis", "rubrics": {"preferred": "Strahlenzystitis"}, "children": []}, {"code": "N30.8", "kind": "category", "label": "Sonstige Zystitis", "rubrics": {"preferred": "Sonstige Zystitis"}, "children": [{"code": "N30.80", "kind": "category", "label": "Abszess der Harnblasenwand", "rubrics": {"preferred": "Abszess der Harnblasenwand", "inclusion": "Harnblasenabszess"}, "children": []}, {"code": "N30.88", "kind": "category", "label": "Sonstige Zystitis", "rubrics": {"preferred": "Sonstige Zystitis"}, "children": []}]}, {"code": "N30.9", "kind": "category", "label": "Zystitis, nicht n채her bezeichnet", "rubrics": {"preferred": "Zystitis, nicht n채her bezeichnet"}, "children": []}]}