{"code": "N33", "kind": "category", "label": "Krankheiten der Harnblase bei anderenorts klassifizierten Krankheiten", "rubrics": {"preferred": "Krankheiten der Harnblase bei anderenorts klassifizierten Krankheiten"}, "children": [{"code": "N33.0", "kind": "category", "label": "Tuberkulöse ZystitisA18.1", "rubrics": {"preferred": "Tuberkulöse ZystitisA18.1"}, "children": []}, {"code": "N33.8", "kind": "category", "label": "Krankheiten der Harnblase bei sonstigen anderenorts klassifizierten Krankheiten", "rubrics": {"preferred": "Krankheiten der Harnblase bei sonstigen anderenorts klassifizierten Krankheiten", "inclusion": "Krankheit der Harnblase bei Schistosomiasis [Bilharziose]B65.-"}, "children": []}]}