{"code": "N97", "kind": "category", "label": "Sterilität der Frau", "rubrics": {"preferred": "Sterilität der Frau", "inclusion": "Sterilität o.n.A. bei der Frau", "exclusion": "InfertilitätN96"}, "children": [{"code": "N97.0", "kind": "category", "label": "Sterilität der Frau in Verbindung mit fehlender Ovulation", "rubrics": {"preferred": "Sterilität der Frau in Verbindung mit fehlender Ovulation"}, "children": []}, {"code": "N97.1", "kind": "category", "label": "Sterilität tubaren Ursprungs bei der Frau", "rubrics": {"preferred": "Sterilität tubaren Ursprungs bei der Frau", "inclusion": "Tubenverschluss"}, "children": []}, {"code": "N97.2", "kind": "category", "label": "Sterilität uterinen Ursprungs bei der Frau", "rubrics": {"preferred": "Sterilität uterinen Ursprungs bei der Frau", "inclusion": "Nichtimplantation einer Eizelle"}, "children": []}, {"code": "N97.3", "kind": "category", "label": "Sterilität zervikalen Ursprungs bei der Frau", "rubrics": {"preferred": "Sterilität zervikalen Ursprungs bei der Frau"}, "children": []}, {"code": "N97.4", "kind": "category", "label": "Sterilität der Frau im Zusammenhang mit Faktoren des Partners", "rubrics": {"preferred": "Sterilität der Frau im Zusammenhang mit Faktoren des Partners"}, "children": []}, {"code": "N97.8", "kind": "category", "label": "Sterilität sonstigen Ursprungs bei der Frau", "rubrics": {"preferred": "Sterilität sonstigen Ursprungs bei der Frau"}, "children": []}, {"code": "N97.9", "kind": "category", "label": "Sterilität der Frau, nicht näher bezeichnet", "rubrics": {"preferred": "Sterilität der Frau, nicht näher bezeichnet"}, "children": []}]}