{
  "code": "L66",
  "kind": "category",
  "label": "Narbige Alopezie [Haarausfall mit Narbenbildung]",
  "rubrics": {
    "preferred": "Narbige Alopezie [Haarausfall mit Narbenbildung]"
  },
  "children": [
    {
      "code": "L66.0",
      "kind": "category",
      "label": "Pseudopelade Brocq",
      "rubrics": {
        "preferred": "Pseudopelade Brocq"
      },
      "children": []
    },
    {
      "code": "L66.1",
      "kind": "category",
      "label": "Lichen planopilaris",
      "rubrics": {
        "preferred": "Lichen planopilaris",
        "inclusion": "Lichen ruber follicularis"
      },
      "children": []
    },
    {
      "code": "L66.2",
      "kind": "category",
      "label": "Folliculitis decalvans",
      "rubrics": {
        "preferred": "Folliculitis decalvans"
      },
      "children": []
    },
    {
      "code": "L66.3",
      "kind": "category",
      "label": "Folliculitis et Perifolliculitis capitis abscedens et suffodiens [Hoffmann]",
      "rubrics": {
        "preferred": "Folliculitis et Perifolliculitis capitis abscedens et suffodiens [Hoffmann]"
      },
      "children": []
    },
    {
      "code": "L66.4",
      "kind": "category",
      "label": "Atrophodermia vermiculata",
      "rubrics": {
        "preferred": "Atrophodermia vermiculata",
        "inclusion": "Ulerythema acneiforme"
      },
      "children": []
    },
    {
      "code": "L66.8",
      "kind": "category",
      "label": "Sonstige narbige Alopezie",
      "rubrics": {
        "preferred": "Sonstige narbige Alopezie"
      },
      "children": []
    },
    {
      "code": "L66.9",
      "kind": "category",
      "label": "Narbige Alopezie, nicht näher bezeichnet",
      "rubrics": {
        "preferred": "Narbige Alopezie, nicht näher bezeichnet"
      },
      "children": []
    }
  ]
}