{
  "code": "Z96.8",
  "kind": "category",
  "label": "Vorhandensein von sonstigen n채her bezeichneten funktionellen Implantaten",
  "rubrics": {
    "preferred": "Vorhandensein von sonstigen n채her bezeichneten funktionellen Implantaten"
  },
  "children": [
    {
      "code": "Z96.80",
      "kind": "category",
      "label": "Vorhandensein eines Bronchialstents",
      "rubrics": {
        "preferred": "Vorhandensein eines Bronchialstents"
      },
      "children": []
    },
    {
      "code": "Z96.81",
      "kind": "category",
      "label": "Vorhandensein eines Trachealstents",
      "rubrics": {
        "preferred": "Vorhandensein eines Trachealstents"
      },
      "children": []
    },
    {
      "code": "Z96.88",
      "kind": "category",
      "label": "Vorhandensein von sonstigen n채her bezeichneten funktionellen Implantaten",
      "rubrics": {
        "preferred": "Vorhandensein von sonstigen n채her bezeichneten funktionellen Implantaten"
      },
      "children": []
    }
  ]
}