{"code": "J01", "kind": "category", "label": "Akute Sinusitis", "rubrics": {"preferred": "Akute Sinusitis", "inclusion": "Infektion\n\t\t\t\takut, (Nasen-) Nebenhöhlen", "coding-hint": "Soll der Infektionserreger angegeben werden, ist eine zusätzliche Schlüsselnummer (B95-B98) zu benutzen.", "exclusion": "Sinusitis, chronisch oder o.n.A.J32.-"}, "children": [{"code": "J01.0", "kind": "category", "label": "Akute Sinusitis maxillaris", "rubrics": {"preferred": "Akute Sinusitis maxillaris", "inclusion": "Akute Kieferhöhlenentzündung"}, "children": []}, {"code": "J01.1", "kind": "category", "label": "Akute Sinusitis frontalis", "rubrics": {"preferred": "Akute Sinusitis frontalis"}, "children": []}, {"code": "J01.2", "kind": "category", "label": "Akute Sinusitis ethmoidalis", "rubrics": {"preferred": "Akute Sinusitis ethmoidalis"}, "children": []}, {"code": "J01.3", "kind": "category", "label": "Akute Sinusitis sphenoidalis", "rubrics": {"preferred": "Akute Sinusitis sphenoidalis"}, "children": []}, {"code": "J01.4", "kind": "category", "label": "Akute Pansinusitis", "rubrics": {"preferred": "Akute Pansinusitis"}, "children": []}, {"code": "J01.8", "kind": "category", "label": "Sonstige akute Sinusitis", "rubrics": {"preferred": "Sonstige akute Sinusitis", "inclusion": "Akute Sinusitis mit Beteiligung von mehr als einer Nasennebenhöhle, ausgenommen Pansinusitis"}, "children": []}, {"code": "J01.9", "kind": "category", "label": "Akute Sinusitis, nicht näher bezeichnet", "rubrics": {"preferred": "Akute Sinusitis, nicht näher bezeichnet"}, "children": []}]}