{"code": "K57.9", "kind": "category", "label": "Divertikelkrankheit des Darmes, Teil nicht näher bezeichnet, ohne Perforation oder Abszess", "rubrics": {"preferred": "Divertikelkrankheit des Darmes, Teil nicht näher bezeichnet, ohne Perforation oder Abszess", "inclusion": "Divertikulose des Darmes o.n.A."}, "children": [{"code": "K57.90", "kind": "category", "label": "Divertikulose des Darmes, Teil nicht näher bezeichnet, ohne Perforation, Abszess oder Angabe einer Blutung", "rubrics": {"preferred": "Divertikulose des Darmes, Teil nicht näher bezeichnet, ohne Perforation, Abszess oder Angabe einer Blutung"}, "children": []}, {"code": "K57.91", "kind": "category", "label": "Divertikulose des Darmes, Teil nicht näher bezeichnet, ohne Perforation oder Abszess, mit Blutung", "rubrics": {"preferred": "Divertikulose des Darmes, Teil nicht näher bezeichnet, ohne Perforation oder Abszess, mit Blutung"}, "children": []}, {"code": "K57.92", "kind": "category", "label": "Divertikulitis des Darmes, Teil nicht näher bezeichnet, ohne Perforation, Abszess oder Angabe einer Blutung", "rubrics": {"preferred": "Divertikulitis des Darmes, Teil nicht näher bezeichnet, ohne Perforation, Abszess oder Angabe einer Blutung"}, "children": []}, {"code": "K57.93", "kind": "category", "label": "Divertikulitis des Darmes, Teil nicht näher bezeichnet, ohne Perforation oder Abszess, mit Blutung", "rubrics": {"preferred": "Divertikulitis des Darmes, Teil nicht näher bezeichnet, ohne Perforation oder Abszess, mit Blutung"}, "children": []}]}