{"code": "C04", "kind": "category", "label": "Bösartige Neubildung des Mundbodens", "rubrics": {"preferred": "Bösartige Neubildung des Mundbodens"}, "children": [{"code": "C04.0", "kind": "category", "label": "Vorderer Teil des Mundbodens", "rubrics": {"preferredLong": "Bösartige Neubildung: Vorderer Teil des Mundbodens", "preferred": "Vorderer Teil des Mundbodens", "inclusion": "Von vorn bis zum Prämolar-Eckzahn-Übergang"}, "children": []}, {"code": "C04.1", "kind": "category", "label": "Seitlicher Teil des Mundbodens", "rubrics": {"preferredLong": "Bösartige Neubildung: Seitlicher Teil des Mundbodens", "preferred": "Seitlicher Teil des Mundbodens"}, "children": []}, {"code": "C04.8", "kind": "category", "label": "Mundboden, mehrere Teilbereiche überlappend", "rubrics": {"preferredLong": "Bösartige Neubildung: Mundboden, mehrere Teilbereiche überlappend", "preferred": "Mundboden, mehrere Teilbereiche überlappend", "text": "[Siehe Hinweis 5 am Anfang dieses Kapitels]"}, "children": []}, {"code": "C04.9", "kind": "category", "label": "Mundboden, nicht näher bezeichnet", "rubrics": {"preferredLong": "Bösartige Neubildung: Mundboden, nicht näher bezeichnet", "preferred": "Mundboden, nicht näher bezeichnet"}, "children": []}]}