{"code": "C30", "kind": "category", "label": "Bösartige Neubildung der Nasenhöhle und des Mittelohres", "rubrics": {"preferred": "Bösartige Neubildung der Nasenhöhle und des Mittelohres"}, "children": [{"code": "C30.0", "kind": "category", "label": "Nasenhöhle", "rubrics": {"preferredLong": "Bösartige Neubildung: Nasenhöhle", "preferred": "Nasenhöhle", "inclusion": "Vestibulum nasi", "exclusion": "NasenbeinC41.02"}, "children": []}, {"code": "C30.1", "kind": "category", "label": "Mittelohr", "rubrics": {"preferredLong": "Bösartige Neubildung: Mittelohr", "preferred": "Mittelohr", "inclusion": "Tuba auditiva [Eustachio]", "exclusion": "OhrknorpelC49.0"}, "children": []}]}