{"code": "F50.2", "kind": "category", "label": "Bulimia nervosa", "rubrics": {"preferred": "Bulimia nervosa", "definition": "Ein Syndrom, das durch wiederholte Anfälle von Heißhunger und eine übertriebene Beschäftigung mit der Kontrolle des Körpergewichts charakterisiert ist. Dies führt zu einem Verhaltensmuster von Essanfällen und Erbrechen oder Gebrauch von Abführmitteln. Viele psychische Merkmale dieser Störung ähneln denen der Anorexia nervosa, so die übertriebene Sorge um Körperform und Gewicht. Wiederholtes Erbrechen kann zu Elektrolytstörungen und körperlichen Komplikationen führen. Häufig lässt sich in der Anamnese eine frühere Episode einer Anorexia nervosa mit einem Intervall von einigen Monaten bis zu mehreren Jahren nachweisen.", "inclusion": "Hyperorexia nervosa"}, "children": []}