{"code": "F93.0", "kind": "category", "label": "Emotionale Störung mit Trennungsangst des Kindesalters", "rubrics": {"preferred": "Emotionale Störung mit Trennungsangst des Kindesalters", "definition": "Eine Störung mit Trennungsangst soll nur dann diagnostiziert werden, wenn die Furcht vor Trennung den Kern der Angst darstellt und wenn eine solche Angst erstmals während der frühen Kindheit auftrat. Sie unterscheidet sich von normaler Trennungsangst durch eine unübliche Ausprägung, eine abnorme Dauer über die typische Altersstufe hinaus und durch deutliche Probleme in sozialen Funktionen.", "exclusion": "Störung mit sozialer Überempfindlichkeit des KindesaltersF93.2"}, "children": []}