{"code": "S01.84", "kind": "category", "label": "Weichteilschaden I. Grades bei geschlossener Fraktur oder Luxation des Kopfes", "rubrics": {"preferred": "Weichteilschaden I. Grades bei geschlossener Fraktur oder Luxation des Kopfes", "text": "Oberflächliche Schürfung, einfache bis mittelschwere Bruchform", "note": "Geschlossene Frakturen oder Luxationen mit Weichteilschaden 0. Grades (geringer Weichteilschaden, einfache Bruchform) oder nicht näher bezeichneten Grades erhalten keine zusätzliche Schlüsselnummer."}, "children": []}